arcadia/.env.production
arcadia/__init__.py
arcadia/client.py
arcadia/modules/__init__.py
arcadia/modules/billing/__init__.py
arcadia/modules/billing/invoices.py
arcadia/modules/billing/stripe_setup.py
arcadia/modules/logger/__init__.py
arcadia/modules/logger/factory.py
arcadia/modules/logger/interface.py
arcadia/modules/login/__init__.py
arcadia/modules/login/__main__.py
arcadia/modules/login/auth.py
arcadia/modules/login/cli.py
arcadia/modules/login/config.py
arcadia/utils/__init__.py
arcadia/utils/settings.py
arcadia_sdk-0.3.8.dist-info/LICENSE
arcadia_sdk-0.3.8.dist-info/METADATA
arcadia_sdk-0.3.8.dist-info/WHEEL
arcadia_sdk-0.3.8.dist-info/entry_points.txt
arcadia_sdk-0.3.8.dist-info/RECORD
